google_sheets_local/__init__.py
google_sheets_local/constants_src_google_sheet_local.py
google_sheets_local/google_sheet.py
google_sheets_local/google_sheets_local.py
google_sheets_local-0.0.3.dist-info/METADATA
google_sheets_local-0.0.3.dist-info/WHEEL
google_sheets_local-0.0.3.dist-info/top_level.txt
google_sheets_local-0.0.3.dist-info/RECORD
