Metadata-Version: 2.4
Name: google-sheets-local
Version: 0.0.3
Summary: PyPI Package for Circles google-sheets-local Python
Home-page: https://github.com/circles-zone/google-sheets-local-python-package
Author: Circles
Author-email: info@circlez.ai
Classifier: Programming Language :: Python :: 3
Classifier: Operating System :: OS Independent
Requires-Dist: python-sdk-remote
Requires-Dist: logger-local
Requires-Dist: user-external-local>=0.0.114
Requires-Dist: api-management-local>=0.0.80
Requires-Dist: google-auth-oauthlib>=1.2.2
Requires-Dist: google-auth-httplib2>=0.2.0
Requires-Dist: google-api-python-client>=2.128.0
Requires-Dist: user-external-local>=0.0.149
Requires-Dist: api-management-local>=0.0.80
Requires-Dist: fields-local>=0.0.9
Requires-Dist: database_mysql_local>=0.1.23
Requires-Dist: storage_local>=0.1.59
Requires-Dist: google_account_local>=0.0.27
Requires-Dist: email_address_local>=0.0.65
Requires-Dist: data-source-local>=0.0.17
Dynamic: author
Dynamic: author-email
Dynamic: classifier
Dynamic: description
Dynamic: description-content-type
Dynamic: home-page
Dynamic: requires-dist
Dynamic: summary
